odoo/addons/shopinvader_customer_invoicing_mode/README.rst
odoo/addons/shopinvader_customer_invoicing_mode/__init__.py
odoo/addons/shopinvader_customer_invoicing_mode/__manifest__.py
odoo/addons/shopinvader_customer_invoicing_mode/i18n/shopinvader_customer_invoicing_mode.pot
odoo/addons/shopinvader_customer_invoicing_mode/readme/CONTRIBUTORS.rst
odoo/addons/shopinvader_customer_invoicing_mode/readme/DESCRIPTION.rst
odoo/addons/shopinvader_customer_invoicing_mode/services/__init__.py
odoo/addons/shopinvader_customer_invoicing_mode/services/customer.py
odoo/addons/shopinvader_customer_invoicing_mode/static/description/index.html
odoo/addons/shopinvader_customer_invoicing_mode/tests/__init__.py
odoo/addons/shopinvader_customer_invoicing_mode/tests/test_customer.py
odoo14_addon_shopinvader_customer_invoicing_mode-14.0.1.0.1.dev3.dist-info/METADATA
odoo14_addon_shopinvader_customer_invoicing_mode-14.0.1.0.1.dev3.dist-info/WHEEL
odoo14_addon_shopinvader_customer_invoicing_mode-14.0.1.0.1.dev3.dist-info/top_level.txt
odoo14_addon_shopinvader_customer_invoicing_mode-14.0.1.0.1.dev3.dist-info/RECORD
