Metadata-Version: 2.1
Name: odoo14-addon-shopinvader_customer_invoicing_mode
Version: 14.0.1.0.1.dev3
Summary: Glue module to expose the invoicing_mode field to shopinvader
Home-page: https://github.com/shopinvader/odoo-shopinvader
Author: Camptocamp
License: AGPL-3
Classifier: Programming Language :: Python
Classifier: Framework :: Odoo
Classifier: Framework :: Odoo :: 14.0
Classifier: License :: OSI Approved :: GNU Affero General Public License v3
Requires-Python: >=3.6
Requires-Dist: odoo14-addon-account-invoice-base-invoicing-mode
Requires-Dist: odoo14-addon-shopinvader
Requires-Dist: odoo <14.1dev,>=14.0a
